weather_forcaster/main.py
weather_forcaster/utils.py
weather_forcaster-1.0.2.dist-info/LICENSE
weather_forcaster-1.0.2.dist-info/METADATA
weather_forcaster-1.0.2.dist-info/WHEEL
weather_forcaster-1.0.2.dist-info/entry_points.txt
weather_forcaster-1.0.2.dist-info/top_level.txt
weather_forcaster-1.0.2.dist-info/RECORD
